plugy/__init__.py
plugy/_version.py
plugy/exp.py
plugy/misc.py
plugy/data/__init__.py
plugy/data/bd.py
plugy/data/config.py
plugy/data/plug.py
plugy/data/pmt.py
plugy/test/__init__.py
plugy/test/test_bd.py
plugy/test/test_exp.py
plugy/test/test_plug.py
plugy/test/test_pmt.py
plugy-1.1.0.dist-info/LICENSE
plugy-1.1.0.dist-info/METADATA
plugy-1.1.0.dist-info/WHEEL
plugy-1.1.0.dist-info/top_level.txt
plugy-1.1.0.dist-info/RECORD
