Metadata-Version: 2.1
Name: plugy
Version: 1.1.0
Summary: Processing plug microfluidics data
Home-page: https://github.com/saezlab/plugy
Author: Dénes Türei, Nicolas Peschke, Olga Ivanova
Author-email: turei.denes@gmail.com
License: GPLv3
Classifier: Development Status :: 5 - Production/Stable
Classifier: Intended Audience :: Developers
Classifier: Intended Audience :: Science/Research
Classifier: License :: OSI Approved :: GNU General Public License v3 (GPLv3)
Classifier: Operating System :: OS Independent
Classifier: Programming Language :: Python
Classifier: Natural Language :: English
Classifier: Topic :: Scientific/Engineering :: Bio-Informatics
Classifier: Topic :: Scientific/Engineering :: Medical Science Apps.
License-File: LICENSE
Requires-Dist: seaborn
Requires-Dist: matplotlib
Requires-Dist: statsmodels
Requires-Dist: scipy
Requires-Dist: pandas
Requires-Dist: numpy
Requires-Dist: scikit-image
Requires-Dist: tqdm
